{
  "user": {
    "age": 99,
    "ambassador": false,
    "autoStrideEnabled": true,
    "avatar": "https://via.placeholder.com/100",
    "avatar150": "https://via.placeholder.com/150",
    "avatar640": "https://via.placeholder.com/640",
    "averageDailySteps": 15194,
    "challengesBeta": true,
    "clockTimeDisplayFormat": "24hour",
    "corporate": false,
    "corporateAdmin": false,
    "dateOfBirth": "1997-10-10",
    "displayName": "Joe Doe",
    "displayNameSetting": "name",
    "distanceUnit": "METRIC",
    "encodedId": "46FYTW",
    "features": {
      "exerciseGoal": true
    },
    "firstName": "Joe",
    "foodsLocale": "en_US",
    "fullName": "Joe Doe",
    "gender": "MALE",
    "glucoseUnit": "en_US",
    "height": 173.0,
    "heightUnit": "METRIC",
    "isBugReportEnabled": false,
    "isChild": false,
    "isCoach": false,
    "languageLocale": "en_US",
    "lastName": "Doe",
    "legalTermsAcceptRequired": true,
    "locale": "en_US",
    "memberSince": "2016-01-12",
    "mfaEnabled": false,
    "offsetFromUTCMillis": 3600000,
    "sdkDeveloper": false,
    "sleepTracking": "Normal",
    "startDayOfWeek": "SUNDAY",
    "strideLengthRunning": 107.9,
    "strideLengthRunningType": "auto",
    "strideLengthWalking": 71.8,
    "strideLengthWalkingType": "auto",
    "swimUnit": "METRIC",
    "temperatureUnit": "METRIC",
    "timezone": "Europe/Stockholm",
    "topBadges": [
      {
        "badgeGradientEndColor": "00D3D6",
        "badgeGradientStartColor": "007273",
        "badgeType": "DAILY_STEPS",
        "category": "Daily Steps",
        "cheers": [],
        "dateTime": "2017-10-15",
        "description": "30,000 steps in a day",
        "earnedMessage": "Congrats on earning your first Trail Shoe badge!",
        "encodedId": "228TM5",
        "image100px": "https://badges.fitbit.com/images/badges_new/100px/badge_daily_steps30k.png",
        "image125px": "https://badges.fitbit.com/images/badges_new/125px/badge_daily_steps30k.png",
        "image300px": "https://badges.fitbit.com/images/badges_new/300px/badge_daily_steps30k.png",
        "image50px": "https://badges.fitbit.com/images/badges_new/badge_daily_steps30k.png",
        "image75px": "https://badges.fitbit.com/images/badges_new/75px/badge_daily_steps30k.png",
        "marketingDescription": "You've walked 30,000 steps  And earned the Trail Shoe badge!",
        "mobileDescription": "On the path to fitness, you're gaining some serious ground!",
        "name": "Trail Shoe (30,000 steps in a day)",
        "shareImage640px": "https://badges.fitbit.com/images/badges_new/386px/shareLocalized/en_US/badge_daily_steps30k.png",
        "shareText": "I took 30,000 steps and earned the Trail Shoe badge! #Fitbit",
        "shortDescription": "30,000 steps",
        "shortName": "Magic Mocked Shoe",
        "timesAchieved": 5,
        "value": 30000
      },
      {
        "badgeGradientEndColor": "FF677C",
        "badgeGradientStartColor": "D24958",
        "badgeType": "LIFETIME_DISTANCE",
        "category": "Lifetime Distance",
        "cheers": [],
        "dateTime": "2021-03-14",
        "description": "9,289 lifetime kilometers",
        "earnedMessage": "Whoa! You've earned the Russian Railway badge!",
        "encodedId": "22B8L7",
        "image100px": "https://badges.fitbit.com/images/badges_new/100px/badge_lifetime_miles5772.png",
        "image125px": "https://badges.fitbit.com/images/badges_new/125px/badge_lifetime_miles5772.png",
        "image300px": "https://badges.fitbit.com/images/badges_new/300px/badge_lifetime_miles5772.png",
        "image50px": "https://badges.fitbit.com/images/badges_new/badge_lifetime_miles5772.png",
        "image75px": "https://badges.fitbit.com/images/badges_new/75px/badge_lifetime_miles5772.png",
        "marketingDescription": "By reaching 9,289 lifetime kilometers, you've earned the Russian Railway badge!",
        "mobileDescription": "You're en route to destination fitness! You've walked the length of the Trans-Siberian Railway in Russia!",
        "name": "Russian Railway (9,289 lifetime kilometers)",
        "shareImage640px": "https://badges.fitbit.com/images/badges_new/386px/shareLocalized/en_US/badge_lifetime_miles5772_km.png",
        "shareText": "I covered 9,289 kilometers with my #Fitbit and earned the Russian Railway badge.",
        "shortDescription": "9,289 kilometers",
        "shortName": "Mocked Russian Railway",
        "timesAchieved": 1,
        "unit": "KILOMETERS",
        "value": 9289
      }
    ],
    "waterUnit": "METRIC",
    "waterUnitName": "ml",
    "weight": 100.2,
    "weightUnit": "METRIC"
  }
}
